alignment_tool/__init__.py
alignment_tool/__main__.py
alignment_tool/py.typed
alignment_tool-1.0.0.dist-info/entry_points.txt
alignment_tool-1.0.0.dist-info/LICENSE
alignment_tool-1.0.0.dist-info/WHEEL
alignment_tool-1.0.0.dist-info/METADATA
alignment_tool-1.0.0.dist-info/RECORD
